Workbook
Name StatusList: Lookups!$A$2:$A$8
Name TriggerList: Lookups!$B$2:$B$8
Name PhaseList: Lookups!$C$2:$C$3
Name ApprovalList: Lookups!$D$2:$D$5
Name InvoiceList: Lookups!$E$2:$E$4
Name ProjectCode: 'Project Setup'!$B$3
Name ProjectName: 'Project Setup'!$B$4
Name ClientName: 'Project Setup'!$B$5
Name OriginalContractSum: 'Project Setup'!$B$9
Name BuilderName: 'Project Setup'!$B$10
Name BuilderLegalEntity: 'Project Setup'!$B$11
Name BuilderABN: 'Project Setup'!$B$12
Name BuilderLicense: 'Project Setup'!$B$13

Sheet Variations
A1: VARIATION REGISTER
A2: IDENTIFICATION & SCOPE | H2: COST TO ME (CONFIDENTIAL — INTERNAL ONLY) | O2: PRICE TO CLIENT (appears on notice) | T2: NOTICE / APPROVAL / INVOICING
A3: VAR # | B3: Date Raised | C3: Status | D3: Phase | E3: Trigger | F3: Short description | G3: Detailed scope | H3: Materials $ | I3: Labour $ | J3: Subcontractor $ | K3: Plant / hire $ | L3: Other $ | M3: Cost to me (total) | N3: Markup % | O3: Price (ex GST) | P3: GST | Q3: Price (inc GST) | R3: Time impact (days) | S3: Margin $ | T3: Notice v1 issued | U3: Notice v2 issued | V3: Client approval date | W3: Approval method | X3: Approved by (name) | Y3: Invoice / claim # | Z3: Invoice method | AA3: Date invoiced | AB3: Dropbox folder | AC3: Notes
M4: =IFERROR(SUM(H4:L4),0) | O4: =IF(AND(ISNUMBER(M4),ISNUMBER(N4)),M4*(1+N4),"") | P4: =IF(ISNUMBER(O4),O4*0.1,"") | Q4: =IF(AND(ISNUMBER(O4),ISNUMBER(P4)),O4+P4,"") | S4: =IF(AND(ISNUMBER(O4),ISNUMBER(M4)),O4-M4,"")
M5: =IFERROR(SUM(H5:L5),0) | O5: =IF(AND(ISNUMBER(M5),ISNUMBER(N5)),M5*(1+N5),"") | P5: =IF(ISNUMBER(O5),O5*0.1,"") | Q5: =IF(AND(ISNUMBER(O5),ISNUMBER(P5)),O5+P5,"") | S5: =IF(AND(ISNUMBER(O5),ISNUMBER(M5)),O5-M5,"")
M6: =IFERROR(SUM(H6:L6),0) | O6: =IF(AND(ISNUMBER(M6),ISNUMBER(N6)),M6*(1+N6),"") | P6: =IF(ISNUMBER(O6),O6*0.1,"") | Q6: =IF(AND(ISNUMBER(O6),ISNUMBER(P6)),O6+P6,"") | S6: =IF(AND(ISNUMBER(O6),ISNUMBER(M6)),O6-M6,"")
M7: =IFERROR(SUM(H7:L7),0) | O7: =IF(AND(ISNUMBER(M7),ISNUMBER(N7)),M7*(1+N7),"") | P7: =IF(ISNUMBER(O7),O7*0.1,"") | Q7: =IF(AND(ISNUMBER(O7),ISNUMBER(P7)),O7+P7,"") | S7: =IF(AND(ISNUMBER(O7),ISNUMBER(M7)),O7-M7,"")
M8: =IFERROR(SUM(H8:L8),0) | O8: =IF(AND(ISNUMBER(M8),ISNUMBER(N8)),M8*(1+N8),"") | P8: =IF(ISNUMBER(O8),O8*0.1,"") | Q8: =IF(AND(ISNUMBER(O8),ISNUMBER(P8)),O8+P8,"") | S8: =IF(AND(ISNUMBER(O8),ISNUMBER(M8)),O8-M8,"")
M9: =IFERROR(SUM(H9:L9),0) | O9: =IF(AND(ISNUMBER(M9),ISNUMBER(N9)),M9*(1+N9),"") | P9: =IF(ISNUMBER(O9),O9*0.1,"") | Q9: =IF(AND(ISNUMBER(O9),ISNUMBER(P9)),O9+P9,"") | S9: =IF(AND(ISNUMBER(O9),ISNUMBER(M9)),O9-M9,"")
M10: =IFERROR(SUM(H10:L10),0) | O10: =IF(AND(ISNUMBER(M10),ISNUMBER(N10)),M10*(1+N10),"") | P10: =IF(ISNUMBER(O10),O10*0.1,"") | Q10: =IF(AND(ISNUMBER(O10),ISNUMBER(P10)),O10+P10,"") | S10: =IF(AND(ISNUMBER(O10),ISNUMBER(M10)),O10-M10,"")
M11: =IFERROR(SUM(H11:L11),0) | O11: =IF(AND(ISNUMBER(M11),ISNUMBER(N11)),M11*(1+N11),"") | P11: =IF(ISNUMBER(O11),O11*0.1,"") | Q11: =IF(AND(ISNUMBER(O11),ISNUMBER(P11)),O11+P11,"") | S11: =IF(AND(ISNUMBER(O11),ISNUMBER(M11)),O11-M11,"")
M12: =IFERROR(SUM(H12:L12),0) | O12: =IF(AND(ISNUMBER(M12),ISNUMBER(N12)),M12*(1+N12),"") | P12: =IF(ISNUMBER(O12),O12*0.1,"") | Q12: =IF(AND(ISNUMBER(O12),ISNUMBER(P12)),O12+P12,"") | S12: =IF(AND(ISNUMBER(O12),ISNUMBER(M12)),O12-M12,"")
M13: =IFERROR(SUM(H13:L13),0) | O13: =IF(AND(ISNUMBER(M13),ISNUMBER(N13)),M13*(1+N13),"") | P13: =IF(ISNUMBER(O13),O13*0.1,"") | Q13: =IF(AND(ISNUMBER(O13),ISNUMBER(P13)),O13+P13,"") | S13: =IF(AND(ISNUMBER(O13),ISNUMBER(M13)),O13-M13,"")
M14: =IFERROR(SUM(H14:L14),0) | O14: =IF(AND(ISNUMBER(M14),ISNUMBER(N14)),M14*(1+N14),"") | P14: =IF(ISNUMBER(O14),O14*0.1,"") | Q14: =IF(AND(ISNUMBER(O14),ISNUMBER(P14)),O14+P14,"") | S14: =IF(AND(ISNUMBER(O14),ISNUMBER(M14)),O14-M14,"")
M15: =IFERROR(SUM(H15:L15),0) | O15: =IF(AND(ISNUMBER(M15),ISNUMBER(N15)),M15*(1+N15),"") | P15: =IF(ISNUMBER(O15),O15*0.1,"") | Q15: =IF(AND(ISNUMBER(O15),ISNUMBER(P15)),O15+P15,"") | S15: =IF(AND(ISNUMBER(O15),ISNUMBER(M15)),O15-M15,"")
... M53: =IFERROR(SUM(H53:L53),0) | O53: =IF(AND(ISNUMBER(M53),ISNUMBER(N53)),M53*(1+N53),"") | P53: =IF(ISNUMBER(O53),O53*0.1,"") | Q53: =IF(AND(ISNUMBER(O53),ISNUMBER(P53)),O53+P53,"") | S53: =IF(AND(ISNUMBER(O53),ISNUMBER(M53)),O53-M53,"")
A55: CONFIDENTIAL columns (red header band) contain cost-to-me data and MUST NEVER be shared with the client. CLIENT columns (green header band) are the only price figures that appear on the formal Variation Notice.

Sheet Lookups
A1: Status | B1: Trigger | C1: Phase | D1: ApprovalMethod | E1: InvoiceMethod
A2: RAISED | B2: Client request | C2: 1 — RAISED | D2: Email confirmation | E2: Next progress claim
A3: PRICED | B3: Site condition | C3: 2 — FINALISED | D3: Signed PDF | E3: Standalone invoice
A4: FINALISED | B4: Council / certifier | D4: Signed hardcopy | E4: Not yet invoiced
A5: APPROVED | B5: Architect / engineer | D5: Verbal + email confirm
A6: INVOICED | B6: Supplier-driven
A7: CANCELLED | B7: Builder-initiated
A8: ON HOLD | B8: Other

Sheet Project Setup
A1: PROJECT SETUP
A3: Project code | B3: (e.g. 42SMITH)
A4: Project name / site address
A5: Client name(s)
A6: Client email
A7: Client phone
A8: Contract date
A9: Original contract sum (inc GST) | B9: 0
A10: Builder name (brand) | B10: Renovate 8
A11: Builder legal entity (licence holder) | B11: Gold and Eagle Constructions
A12: Builder ABN | B12: 72 098 695 446
A13: Builder NSW Contractor Licence # | B13: 139701C
A14: Builder address | B14: 62 Budyan Road, Grays Point NSW 2232
A15: Builder contact email | B15: paul@renovate8.com.au
A16: Builder contact phone | B16: 0404 899 899
A17: Contract form | B17: MBA NSW Residential Building Contract
A18: Dropbox root for project
A19: Default markup % | B19: (leave blank — set per variation)

Sheet Summary
A1: PROJECT SUMMARY
A3: Project code | B3: =ProjectCode
A4: Project name / address | B4: =ProjectName
A5: Client | B5: =ClientName
A7: Original contract sum (inc GST) | B7: =OriginalContractSum | C7: From Project Setup
A8: Variations RAISED (count) | B8: =COUNTIF(Variations!C4:C53,"RAISED") | C8: Phase 1 issued
A9: Variations FINALISED+ (count) | B9: =COUNTIFS(Variations!C4:C53,"<>RAISED",Variations!C4:C53,"<>CANCELLED",Variations!C4:C53,"<>ON HOLD",Variations!C4:C53,"<>") | C9: Priced through to invoiced
A10: Variations CANCELLED (count) | B10: =COUNTIF(Variations!C4:C53,"CANCELLED")
A12: Total approved variations (inc GST) | B12: =IFERROR(SUMIFS(Variations!Q4:Q53,Variations!C4:C53,"APPROVED")+SUMIFS(Variations!Q4:Q53,Variations!C4:C53,"INVOICED"),0) | C12: Sum of APPROVED + INVOICED only
A13: Total pending variations (inc GST) | B13: =IFERROR(SUMIFS(Variations!Q4:Q53,Variations!C4:C53,"RAISED")+SUMIFS(Variations!Q4:Q53,Variations!C4:C53,"PRICED")+SUMIFS(Variations!Q4:Q53,Variations!C4:C53,"FINALISED"),0) | C13: Not yet client-approved
A15: Revised contract sum (approved only) | B15: =B6+B11 | C15: Original + approved variations
A16: Revised contract sum (incl. pending) | B16: =B6+B11+B12 | C16: Worst case — if everything pending also approves
A18: Total cost-to-me (CONFIDENTIAL) | B18: =IFERROR(SUMIFS(Variations!M4:M53,Variations!C4:C53,"APPROVED")+SUMIFS(Variations!M4:M53,Variations!C4:C53,"INVOICED"),0) | C18: Internal — DO NOT share
A19: Total margin (CONFIDENTIAL) | B19: =IFERROR(SUMIFS(Variations!S4:S53,Variations!C4:C53,"APPROVED")+SUMIFS(Variations!S4:S53,Variations!C4:C53,"INVOICED"),0) | C19: Internal — DO NOT share
A20: Average markup % (approved) | B20: =IFERROR(AVERAGEIFS(Variations!N4:N53,Variations!C4:C53,"APPROVED"),"") | C20: Internal
A21: Total time impact (days) | B21: =IFERROR(SUM(Variations!R4:R53),0) | C21: Across all non-cancelled rows
